bgblur/__init__.py
bgblur/main.py
bgblur-0.1.1.dist-info/LICENSE
bgblur-0.1.1.dist-info/METADATA
bgblur-0.1.1.dist-info/WHEEL
bgblur-0.1.1.dist-info/entry_points.txt
bgblur-0.1.1.dist-info/top_level.txt
bgblur-0.1.1.dist-info/RECORD
